bin/fill_hosts.py
lazy_lxd/__init__.py
lazy_lxd/__main__.py
lazy_lxd/lazy_lxd.py
lib/ansible/__init__.py
lib/ansible/client.py
lib/ansible/execute.py
lib/ansible/playbook.py
lib/inquirer/__init__.py
lib/inquirer/checkbox.py
lib/inquirer/choose.py
lib/inquirer/confirm.py
lib/inquirer/input.py
lib/inquirer/lists.py
lib/inquirer/password.py
lib/keys/__init__.py
lib/keys/create.py
lib/keys/keys.py
lib/keys/search.py
lib/keys/validate.py
lib/logger/__init__.py
lib/logger/initialize.py
lib/lxd/__init__.py
lib/lxd/client.py
lib/lxd/container.py
lib/lxd/execute.py
lib/lxd/image.py
lazy_lxd-1.1.0.dist-info/LICENSE
lazy_lxd-1.1.0.dist-info/METADATA
lazy_lxd-1.1.0.dist-info/WHEEL
lazy_lxd-1.1.0.dist-info/entry_points.txt
lazy_lxd-1.1.0.dist-info/top_level.txt
lazy_lxd-1.1.0.dist-info/RECORD
