Metadata-Version: 2.1
Name: lazy-lxd
Version: 1.1.0
Summary: Easy creating LXD containers with included routine.
Home-page: https://github.com/vladisnik/lazy-lxd
Author: Vladislav Nikitin
Author-email: gomilt@gmail.com
License: MIT
Platform: UNKNOWN
Classifier: Programming Language :: Python :: 3 :: Only
Classifier: Programming Language :: Python :: 3.6
Classifier: Programming Language :: Python :: 3.7
Classifier: Programming Language :: Python :: 3.8
Classifier: License :: OSI Approved :: MIT License
Classifier: Operating System :: POSIX :: Linux
Classifier: Topic :: Terminals
Classifier: Intended Audience :: Developers
Classifier: Intended Audience :: System Administrators
Classifier: Environment :: Console
Requires-Python: >=3.6
Requires-Dist: colorama (>=0.4.3)
Requires-Dist: coolname (>=1.1.0)
Requires-Dist: cryptography (>=2.9.2)
Requires-Dist: halo (>=0.0.29)
Requires-Dist: humanize (>=2.4.0)
Requires-Dist: PyInquirer (>=1.0.3)
Requires-Dist: pylxd (>=2.2.11)
Requires-Dist: python-dateutil (>=2.8.1)
Requires-Dist: python-hosts (>=1.0.0)
